scgen/__init__.py
scgen/_base_components.py
scgen/_scgen.py
scgen/_scgenvae.py
scgen/_utils.py
scgen-2.1.0.dist-info/LICENSE
scgen-2.1.0.dist-info/WHEEL
scgen-2.1.0.dist-info/METADATA
scgen-2.1.0.dist-info/RECORD
