Metadata-Version: 2.1
Name: scgen
Version: 2.1.0
Summary: ScGen - Predicting single cell perturbations.
Home-page: https://github.com/theislab/scgen
License: MIT
Author: Mohammad lotfollahi
Author-email: mohammad.lotfollahi@helmholtz-muenchen.de
Requires-Python: >=3.7,<4.0
Classifier: Development Status :: 4 - Beta
Classifier: Intended Audience :: Science/Research
Classifier: License :: OSI Approved :: MIT License
Classifier: Natural Language :: English
Classifier: Operating System :: MacOS :: MacOS X
Classifier: Operating System :: Microsoft :: Windows
Classifier: Operating System :: POSIX :: Linux
Classifier: Programming Language :: Python :: 3
Classifier: Programming Language :: Python :: 3.10
Classifier: Programming Language :: Python :: 3.7
Classifier: Programming Language :: Python :: 3.8
Classifier: Programming Language :: Python :: 3.9
Classifier: Topic :: Scientific/Engineering :: Bio-Informatics
Provides-Extra: dev
Provides-Extra: docs
Provides-Extra: tutorials
Requires-Dist: adjustText
Requires-Dist: anndata (>=0.7.5)
Requires-Dist: black (>=20.8b1); extra == "dev"
Requires-Dist: codecov (>=2.0.8); extra == "dev"
Requires-Dist: flake8 (>=3.7.7); extra == "dev"
Requires-Dist: importlib-metadata (>=1.0,<2.0); python_version < "3.8"
Requires-Dist: ipython (>=7.1.1); extra == "docs"
Requires-Dist: isort (>=5.7); extra == "dev"
Requires-Dist: jupyter (>=1.0); extra == "dev"
Requires-Dist: leidenalg; extra == "tutorials"
Requires-Dist: loompy (>=3.0.6); extra == "dev" or extra == "tutorials"
Requires-Dist: nbconvert (>=5.4.0); extra == "dev"
Requires-Dist: nbformat (>=4.4.0); extra == "dev"
Requires-Dist: nbsphinx-link; extra == "docs"
Requires-Dist: nbsphinx; extra == "docs"
Requires-Dist: pre-commit (>=2.7.1); extra == "dev"
Requires-Dist: pydata-sphinx-theme (>=0.4.0); extra == "docs"
Requires-Dist: pytest (>=4.4); extra == "dev"
Requires-Dist: python-igraph; extra == "tutorials"
Requires-Dist: scanpy (>=1.6)
Requires-Dist: scanpydoc (>=0.5); extra == "docs"
Requires-Dist: scikit-misc (>=0.1.3); extra == "tutorials"
Requires-Dist: scvi-tools (>=0.15.0)
Requires-Dist: seaborn (>=0.11)
Requires-Dist: sphinx (>=4.1,<4.4); extra == "docs"
Requires-Dist: sphinx-autodoc-typehints; extra == "docs"
Requires-Dist: sphinx-material; extra == "docs"
Requires-Dist: typing_extensions; (python_version < "3.8") and (extra == "docs")
Project-URL: Documentation, https://scgen.readthedocs.io
